django_simplecrud-1.0b16.dist-info/DESCRIPTION.rst
django_simplecrud-1.0b16.dist-info/METADATA
django_simplecrud-1.0b16.dist-info/metadata.json
django_simplecrud-1.0b16.dist-info/RECORD
django_simplecrud-1.0b16.dist-info/top_level.txt
django_simplecrud-1.0b16.dist-info/WHEEL
simplecrud/format.py
simplecrud/tests.py
simplecrud/utils.py
simplecrud/__init__.py
simplecrud/templates/simplecrud/base.html
simplecrud/templates/simplecrud/container.html
simplecrud/templates/simplecrud/copyright.html
simplecrud/templates/simplecrud/footer.html
simplecrud/templates/simplecrud/header.html
simplecrud/templates/simplecrud/logo.html
simplecrud/templates/simplecrud/menu.html
simplecrud/templates/simplecrud/widget/delete.html
simplecrud/templates/simplecrud/widget/form.html
simplecrud/templates/simplecrud/widget/formset.html
simplecrud/templates/simplecrud/widget/links.html
simplecrud/templates/simplecrud/widget/list.html
simplecrud/templates/simplecrud/widget/panels.html
simplecrud/templates/simplecrud/widget/table.html
simplecrud/templates/simplecrud/widget/tabs.html
simplecrud/templates/simplecrud/widget/text.html
simplecrud/templates/simplecrud/widget/value.html
simplecrud/templates/simplecrud/widget/void.html
simplecrud/templates/simplecrud/widget/vtable.html
simplecrud/templatetags/crud_tags.py
simplecrud/templatetags/__init__.py
